{
  "@context": "http://iiif.io/api/presentation/2/context.json",
  "@id": "http://localhost:8000/manifest.json",
  "@type": "sc:Manifest",
  "label": "City of College Park - letter re use of lakelandschool",
  "metadata": [
    {
      "label": "title",
      "value": "City of College Park - letter re use of lakelandschool"
    },
    {
      "label": "publisher",
      "value": "City of College Park"
    },
    {
      "label": "contributor",
      "value": "wilmer"
    },
    {
      "label": "format",
      "value": "image/jpeg"
    },
    {
      "label": "online submission",
      "value": "No"
    }
  ],
  "sequences": [
    {
      "@type": "sc:Sequence",
      "canvases": [
        {
          "@id": "http://localhost:8000/canvas/page-1.json",
          "@type": "sc:Canvas",
          "label": "Page 1",
          "thumbnail": "http://localhost:8000//images/tiles/fad333c21cff5230dc455fb5e7dc4a6e/full/638,/0/default.jpg",
          "height": 1755,
          "width": 1275,
          "images": [
            {
              "@type": "oa:Annotation",
              "motivation": "sc:painting",
              "resource": {
                "@id": "/http://localhost:8000//images/tiles/fad333c21cff5230dc455fb5e7dc4a6e/full/full/0/default.jpg",
                "@type": "dctypes:Image",
                "format": "image/jpeg",
                "height": 1755,
                "width": 1275,
                "service": {
                  "@context": "http://iiif.io/api/image/2/context.json",
                  "@id": "http://localhost:8000//images/tiles/fad333c21cff5230dc455fb5e7dc4a6e",
                  "profile": "http://iiif.io/api/image/2/level0.json"
                }
              },
              "on": "http://localhost:8000/canvas/page-1.json"
            }
          ]
        }
      ]
    }
  ]
}