{
  "@context": "http://iiif.io/api/presentation/2/context.json",
  "@id": "http://localhost:8000/manifest.json",
  "@type": "sc:Manifest",
  "label": "City of College Park - Earl  & Velma Weysandt & Carter Weysandt Eng. Inc. Blocks 1,12-15 &44 (3)",
  "metadata": [
    {
      "label": "title",
      "value": "City of College Park - Earl  & Velma Weysandt & Carter Weysandt Eng. Inc. Blocks 1,12-15 &44 (3)"
    },
    {
      "label": "publisher",
      "value": "City of College Park"
    },
    {
      "label": "contributor",
      "value": "wilmer"
    },
    {
      "label": "format",
      "value": "image/jpeg"
    },
    {
      "label": "online submission",
      "value": "No"
    }
  ],
  "sequences": [
    {
      "@type": "sc:Sequence",
      "canvases": [
        {
          "@id": "http://localhost:8000/canvas/page-1.json",
          "@type": "sc:Canvas",
          "label": "Page 1",
          "thumbnail": "http://localhost:8000//images/tiles/ebd61997015330d149944ad85797faf2/full/426,/0/default.jpg",
          "height": 2466,
          "width": 1704,
          "images": [
            {
              "@type": "oa:Annotation",
              "motivation": "sc:painting",
              "resource": {
                "@id": "/http://localhost:8000//images/tiles/ebd61997015330d149944ad85797faf2/full/full/0/default.jpg",
                "@type": "dctypes:Image",
                "format": "image/jpeg",
                "height": 2466,
                "width": 1704,
                "service": {
                  "@context": "http://iiif.io/api/image/2/context.json",
                  "@id": "http://localhost:8000//images/tiles/ebd61997015330d149944ad85797faf2",
                  "profile": "http://iiif.io/api/image/2/level0.json"
                }
              },
              "on": "http://localhost:8000/canvas/page-1.json"
            }
          ]
        }
      ]
    }
  ]
}